semantic_kernel/__init__.py
semantic_kernel/const.py
semantic_kernel/kernel.py
semantic_kernel/kernel_pydantic.py
semantic_kernel/kernel_types.py
semantic_kernel/py.typed
semantic_kernel/agents/__init__.py
semantic_kernel/agents/__init__.pyi
semantic_kernel/agents/agent.py
semantic_kernel/agents/autogen/README.md
semantic_kernel/agents/autogen/__init__.py
semantic_kernel/agents/autogen/autogen_conversable_agent.py
semantic_kernel/agents/azure_ai/__init__.py
semantic_kernel/agents/azure_ai/agent_content_generation.py
semantic_kernel/agents/azure_ai/agent_thread_actions.py
semantic_kernel/agents/azure_ai/azure_ai_agent.py
semantic_kernel/agents/azure_ai/azure_ai_agent_settings.py
semantic_kernel/agents/azure_ai/azure_ai_agent_utils.py
semantic_kernel/agents/azure_ai/azure_ai_channel.py
semantic_kernel/agents/bedrock/README.md
semantic_kernel/agents/bedrock/__init__.py
semantic_kernel/agents/bedrock/action_group_utils.py
semantic_kernel/agents/bedrock/bedrock_agent.py
semantic_kernel/agents/bedrock/bedrock_agent_base.py
semantic_kernel/agents/bedrock/bedrock_agent_settings.py
semantic_kernel/agents/bedrock/models/__init__.py
semantic_kernel/agents/bedrock/models/bedrock_action_group_model.py
semantic_kernel/agents/bedrock/models/bedrock_agent_event_type.py
semantic_kernel/agents/bedrock/models/bedrock_agent_model.py
semantic_kernel/agents/bedrock/models/bedrock_agent_status.py
semantic_kernel/agents/channels/__init__.py
semantic_kernel/agents/channels/agent_channel.py
semantic_kernel/agents/channels/bedrock_agent_channel.py
semantic_kernel/agents/channels/chat_history_channel.py
semantic_kernel/agents/channels/open_ai_assistant_channel.py
semantic_kernel/agents/chat_completion/__init__.py
semantic_kernel/agents/chat_completion/chat_completion_agent.py
semantic_kernel/agents/copilot_studio/__init__.py
semantic_kernel/agents/copilot_studio/copilot_studio_agent.py
semantic_kernel/agents/copilot_studio/copilot_studio_agent_settings.py
aot_semantic_kernel-1.35.31.dist-info/licenses/LICENSE
aot_semantic_kernel-1.35.31.dist-info/WHEEL
aot_semantic_kernel-1.35.31.dist-info/METADATA
aot_semantic_kernel-1.35.31.dist-info/RECORD
